optimum/pipelines/__init__.py
optimum/pipelines/backend.py
optimum/pipelines/depends.py
optimum/pipelines/factory.py
optimum/pipelines/backends/__init__.py
optimum/pipelines/backends/transformers/__init__.py
optimum/pipelines/backends/transformers/backend.py
optimum/pipelines/backends/transformers/text_generation.py
optimum/pipelines/backends/transformers/translation.py
optimum/pipelines/generated/__init__.py
optimum/pipelines/generated/audio_classification/input.py
optimum/pipelines/generated/audio_classification/output.py
optimum/pipelines/generated/audio_classification/pipeline.py
optimum/pipelines/generated/automatic_speech_recognition/input.py
optimum/pipelines/generated/automatic_speech_recognition/output.py
optimum/pipelines/generated/automatic_speech_recognition/pipeline.py
optimum/pipelines/generated/document_question_answering/input.py
optimum/pipelines/generated/document_question_answering/output.py
optimum/pipelines/generated/document_question_answering/pipeline.py
optimum/pipelines/generated/fill_mask/input.py
optimum/pipelines/generated/fill_mask/output.py
optimum/pipelines/generated/fill_mask/pipeline.py
optimum/pipelines/generated/image_classification/input.py
optimum/pipelines/generated/image_classification/output.py
optimum/pipelines/generated/image_classification/pipeline.py
optimum/pipelines/generated/image_segmentation/input.py
optimum/pipelines/generated/image_segmentation/output.py
optimum/pipelines/generated/image_segmentation/pipeline.py
optimum/pipelines/generated/image_to_image/input.py
optimum/pipelines/generated/image_to_image/output.py
optimum/pipelines/generated/image_to_image/pipeline.py
optimum/pipelines/generated/object_detection/input.py
optimum/pipelines/generated/object_detection/output.py
optimum/pipelines/generated/object_detection/pipeline.py
optimum/pipelines/generated/question_answering/input.py
optimum/pipelines/generated/question_answering/output.py
optimum/pipelines/generated/question_answering/pipeline.py
optimum_pipelines-0.0.1.dist-info/METADATA
optimum_pipelines-0.0.1.dist-info/WHEEL
optimum_pipelines-0.0.1.dist-info/top_level.txt
optimum_pipelines-0.0.1.dist-info/RECORD
